LICENSE.rst
LICENSE_GPL.rst
MANIFEST.in
README.rst
setup.py
src/agx/__init__.py
src/agx.generator.uml.egg-info/PKG-INFO
src/agx.generator.uml.egg-info/SOURCES.txt
src/agx.generator.uml.egg-info/dependency_links.txt
src/agx.generator.uml.egg-info/entry_points.txt
src/agx.generator.uml.egg-info/namespace_packages.txt
src/agx.generator.uml.egg-info/not-zip-safe
src/agx.generator.uml.egg-info/requires.txt
src/agx.generator.uml.egg-info/top_level.txt
src/agx/generator/__init__.py
src/agx/generator/uml/__init__.py
src/agx/generator/uml/configure.py
src/agx/generator/uml/configure.zcml
src/agx/generator/uml/datatypedependent.py
src/agx/generator/uml/exceptions.py
src/agx/generator/uml/generator.rst
src/agx/generator/uml/hierarchy.py
src/agx/generator/uml/interfaces.py
src/agx/generator/uml/profile.py
src/agx/generator/uml/scope.py
src/agx/generator/uml/stereotypes.py
src/agx/generator/uml/tests.py
src/agx/generator/uml/util.py
src/agx/generator/uml/testing/__init__.py
src/agx/generator/uml/testing/data/examplegg.uml
src/agx/generator/uml/testing/data/examplegg.umlclass
src/agx/generator/uml/testing/data/pyegg.profile.uml
src/agx/generator/uml/testing/data/pyegg.umlprofile